parameterized/__init__.py
parameterized/parameterized.py
parameterized/test.py
parameterized-0.9.0.dist-info/LICENSE.txt
parameterized-0.9.0.dist-info/METADATA
parameterized-0.9.0.dist-info/WHEEL
parameterized-0.9.0.dist-info/top_level.txt
parameterized-0.9.0.dist-info/RECORD
