Metadata-Version: 2.1
Name: parameterized
Version: 0.9.0
Summary: Parameterized testing with any Python test framework
Author-email: David Wolever <david@wolever.net>
License: FreeBSD
Project-URL: Homepage, https://github.com/wolever/parameterized
Classifier: Programming Language :: Python :: 3
Classifier: License :: OSI Approved :: BSD License
Requires-Python: >=3.7
Provides-Extra: dev
License-File: LICENSE.txt
